Metadata-Version: 2.1
Name: pybsub
Version: 0.1
Summary: pubsub library for simple ipc
Home-page: https://github.com/nbdy/pybsub
Author: Pascal Eberlein
Author-email: pascal@eberlein.io
License: UNKNOWN
Platform: UNKNOWN
Classifier: Intended Audience :: Developers
Classifier: Topic :: Software Development :: Build Tools
Classifier: License :: OSI Approved :: MIT License
